pybomojo/__init__.py
pybomojo/backends.py
pybomojo/exceptions.py
pybomojo/tool.py
pybomojo-0.3.2.dist-info/LICENSE.txt
pybomojo-0.3.2.dist-info/METADATA
pybomojo-0.3.2.dist-info/WHEEL
pybomojo-0.3.2.dist-info/top_level.txt
pybomojo-0.3.2.dist-info/RECORD
