Metadata-Version: 2.1
Name: pybomojo
Version: 0.3.2
Summary: Python client for boxofficemojo.com
Home-page: https://bitbucket.org/teamdtao/pybomojo
Author: Dan Tao
Author-email: daniel.tao@gmail.com
Requires-Python: >=3.6
License-File: LICENSE.txt
Requires-Dist: beautifulsoup4 (<5,>=4.6.0)
Requires-Dist: requests (<3,>=2.18.1)
